auth_lockout/__init__.py
auth_lockout/admin.py
auth_lockout/apps.py
auth_lockout/middleware.py
auth_lockout/models.py
auth_lockout/migrations/0001_initial.py
auth_lockout/migrations/__init__.py
auth_lockout-0.0.1.dist-info/METADATA
auth_lockout-0.0.1.dist-info/RECORD
auth_lockout-0.0.1.dist-info/WHEEL
auth_lockout-0.0.1.dist-info/top_level.txt
