Metadata-Version: 2.1
Name: auth-lockout
Version: 0.0.1
Summary: Initial commit
Home-page: https://github.com/kbvanzomeren/pypa.git
Author: Kailey
Author-email: author@example.com
License: UNKNOWN
Platform: UNKNOWN
Classifier: Programming Language :: Python :: 3
Classifier: License :: OSI Approved :: MIT License
Classifier: Operating System :: OS Independent
